unitology/__init__.py
unitology/compat.py
unitology/conf.py
unitology/fields.py
unitology/formfields.py
unitology/forms.py
unitology/models.py
unitology/urls.py
unitology/utils.py
unitology/variables.py
unitology/views.py
unitology/widgets.py
unitology/locale/ru/LC_MESSAGES/django.mo
unitology/static/unitology/js/units_change.js
unitology/templates/unitology/height_field.html
unitology/templates/unitology/height_field_imperial.html
unitology/templates/unitology/height_field_metric.html
unitology/templates/unitology/height_multi_field.html
unitology/templates/unitology/length_field.html
unitology/templates/unitology/length_multi_field.html
unitology/templates/unitology/seconds_ext_field.html
unitology/templates/unitology/seconds_field.html
unitology/templates/unitology/weight_field.html
unitology/templates/unitology/weight_field_imperial.html
unitology/templates/unitology/weight_field_metric.html
unitology/templates/unitology/weight_multi_field.html
unitology/templatetags/__init__.py
unitology/templatetags/compat.py
django_unitology-0.0.7.dist-info/AUTHORS
django_unitology-0.0.7.dist-info/LICENSE
django_unitology-0.0.7.dist-info/METADATA
django_unitology-0.0.7.dist-info/WHEEL
django_unitology-0.0.7.dist-info/top_level.txt
django_unitology-0.0.7.dist-info/RECORD
